Workbook

Sheet Dashboard
A1: DPDP Act 2023 Remediation Tracker
A2: Carzonrent India Pvt Ltd. Built from 13 HOD interviews, 8 to 14 October 2026.
A4: Programme start date | C4: 46309 | D4: Input. Changing it moves every action due date.
A5: Main DPDP duties start (approx.) | C5: 46520 | D5: Input. 18 months from 13 Nov 2025 notification; Legal to confirm.
A6: Days remaining | C6: =C5-TODAY() -> 211
A8: Findings | E8: Theme | F8: Gap | G8: Verify | H8: Open
A9: Total findings | C9: =COUNTA('Gap Register'!$A$5:$A$300) -> 58 | E9: Messaging channels | F9: =COUNTIFS('Gap Register'!$C$5:$C$300,E9,'Gap Register'!$E$5:$E$300,"Gap") -> 5 | G9: =COUNTIFS('Gap Register'!$C$5:$C$300,E9,'Gap Register'!$E$5:$E$300,"Verify") -> 0 | H9: =COUNTIFS('Gap Register'!$C$5:$C$300,E9,'Gap Register'!$J$5:$J$300,"<>Closed") -> 5
A10: Confirmed gaps | C10: =COUNTIF('Gap Register'!$E$5:$E$300,"Gap") -> 36 | E10: ID masking | F10: =COUNTIFS('Gap Register'!$C$5:$C$300,E10,'Gap Register'!$E$5:$E$300,"Gap") -> 3 | G10: =COUNTIFS('Gap Register'!$C$5:$C$300,E10,'Gap Register'!$E$5:$E$300,"Verify") -> 2 | H10: =COUNTIFS('Gap Register'!$C$5:$C$300,E10,'Gap Register'!$J$5:$J$300,"<>Closed") -> 5
A11: Items to verify | C11: =COUNTIF('Gap Register'!$E$5:$E$300,"Verify") -> 22 | E11: Local copies | F11: =COUNTIFS('Gap Register'!$C$5:$C$300,E11,'Gap Register'!$E$5:$E$300,"Gap") -> 8 | G11: =COUNTIFS('Gap Register'!$C$5:$C$300,E11,'Gap Register'!$E$5:$E$300,"Verify") -> 2 | H11: =COUNTIFS('Gap Register'!$C$5:$C$300,E11,'Gap Register'!$J$5:$J$300,"<>Closed") -> 10
A12: Closed | C12: =COUNTIF('Gap Register'!$J$5:$J$300,"Closed") -> 0 | E12: Retention | F12: =COUNTIFS('Gap Register'!$C$5:$C$300,E12,'Gap Register'!$E$5:$E$300,"Gap") -> 5 | G12: =COUNTIFS('Gap Register'!$C$5:$C$300,E12,'Gap Register'!$E$5:$E$300,"Verify") -> 8 | H12: =COUNTIFS('Gap Register'!$C$5:$C$300,E12,'Gap Register'!$J$5:$J$300,"<>Closed") -> 13
A13: Open | C13: =C9-C12 -> 58 | E13: Vendor DPAs | F13: =COUNTIFS('Gap Register'!$C$5:$C$300,E13,'Gap Register'!$E$5:$E$300,"Gap") -> 5 | G13: =COUNTIFS('Gap Register'!$C$5:$C$300,E13,'Gap Register'!$E$5:$E$300,"Verify") -> 2 | H13: =COUNTIFS('Gap Register'!$C$5:$C$300,E13,'Gap Register'!$J$5:$J$300,"<>Closed") -> 7
A14: % closed | C14: =IF(C9=0,0,C12/C9) -> 0 | E14: Notice & consent | F14: =COUNTIFS('Gap Register'!$C$5:$C$300,E14,'Gap Register'!$E$5:$E$300,"Gap") -> 2 | G14: =COUNTIFS('Gap Register'!$C$5:$C$300,E14,'Gap Register'!$E$5:$E$300,"Verify") -> 2 | H14: =COUNTIFS('Gap Register'!$C$5:$C$300,E14,'Gap Register'!$J$5:$J$300,"<>Closed") -> 4
E15: Cross-border | F15: =COUNTIFS('Gap Register'!$C$5:$C$300,E15,'Gap Register'!$E$5:$E$300,"Gap") -> 0 | G15: =COUNTIFS('Gap Register'!$C$5:$C$300,E15,'Gap Register'!$E$5:$E$300,"Verify") -> 5 | H15: =COUNTIFS('Gap Register'!$C$5:$C$300,E15,'Gap Register'!$J$5:$J$300,"<>Closed") -> 5
A16: Actions | E16: Sharing & minimisation | F16: =COUNTIFS('Gap Register'!$C$5:$C$300,E16,'Gap Register'!$E$5:$E$300,"Gap") -> 5 | G16: =COUNTIFS('Gap Register'!$C$5:$C$300,E16,'Gap Register'!$E$5:$E$300,"Verify") -> 0 | H16: =COUNTIFS('Gap Register'!$C$5:$C$300,E16,'Gap Register'!$J$5:$J$300,"<>Closed") -> 5
A17: Total actions | C17: =COUNTA('Action Tracker'!$A$5:$A$15) -> 11 | E17: Consent | F17: =COUNTIFS('Gap Register'!$C$5:$C$300,E17,'Gap Register'!$E$5:$E$300,"Gap") -> 1 | G17: =COUNTIFS('Gap Register'!$C$5:$C$300,E17,'Gap Register'!$E$5:$E$300,"Verify") -> 0 | H17: =COUNTIFS('Gap Register'!$C$5:$C$300,E17,'Gap Register'!$J$5:$J$300,"<>Closed") -> 1
A18: Complete | C18: =COUNTIF('Action Tracker'!$J$5:$J$15,"Complete") -> 0 | E18: Physical records | F18: =COUNTIFS('Gap Register'!$C$5:$C$300,E18,'Gap Register'!$E$5:$E$300,"Gap") -> 1 | G18: =COUNTIFS('Gap Register'!$C$5:$C$300,E18,'Gap Register'!$E$5:$E$300,"Verify") -> 0 | H18: =COUNTIFS('Gap Register'!$C$5:$C$300,E18,'Gap Register'!$J$5:$J$300,"<>Closed") -> 1
A19: In progress | C19: =COUNTIF('Action Tracker'!$J$5:$J$15,"In progress") -> 0 | E19: Incident response | F19: =COUNTIFS('Gap Register'!$C$5:$C$300,E19,'Gap Register'!$E$5:$E$300,"Gap") -> 0 | G19: =COUNTIFS('Gap Register'!$C$5:$C$300,E19,'Gap Register'!$E$5:$E$300,"Verify") -> 1 | H19: =COUNTIFS('Gap Register'!$C$5:$C$300,E19,'Gap Register'!$J$5:$J$300,"<>Closed") -> 1
A20: Blocked | C20: =COUNTIF('Action Tracker'!$J$5:$J$15,"Blocked") -> 0 | E20: Data accuracy | F20: =COUNTIFS('Gap Register'!$C$5:$C$300,E20,'Gap Register'!$E$5:$E$300,"Gap") -> 1 | G20: =COUNTIFS('Gap Register'!$C$5:$C$300,E20,'Gap Register'!$E$5:$E$300,"Verify") -> 0 | H20: =COUNTIFS('Gap Register'!$C$5:$C$300,E20,'Gap Register'!$J$5:$J$300,"<>Closed") -> 1
A21: Overdue | C21: =COUNTIFS('Action Tracker'!$F$5:$F$15,"<"&TODAY(),'Action Tracker'!$J$5:$J$15,"<>Complete") -> 0 | E21: Total | F21: =SUM(F9:F20) -> 36 | G21: =SUM(G9:G20) -> 22 | H21: =SUM(H9:H20) -> 58
A22: Average % complete | C22: =AVERAGE('Action Tracker'!$K$5:$K$15) -> 0
A24: Departments by preliminary rating
A25: Critical | C25: =COUNTIF(Departments!$C$5:$C$17,"Critical") -> 2
A26: High | C26: =COUNTIF(Departments!$C$5:$C$17,"High") -> 6
A27: Medium | C27: =COUNTIF(Departments!$C$5:$C$17,"Medium") -> 4
A28: Low | C28: =COUNTIF(Departments!$C$5:$C$17,"Low") -> 1
A29: HOD declarations signed | C29: =COUNTIF(Departments!$H$5:$H$17,"Yes")&" of 13" -> 0 of 13
A31: Retention schedule
A32: Data categories scheduled | C32: =COUNTA('Retention Schedule'!$A$5:$A$28) -> 24
A33: Approved by Legal | C33: =COUNTIF('Retention Schedule'!$N$5:$N$28,"Yes") -> 0
A34: Implemented in systems | C34: =COUNTIF('Retention Schedule'!$M$5:$M$28,"Implemented") -> 0
A35: Statutory floors | C35: =COUNTIF('Retention Schedule'!$H$5:$H$28,"Statutory floor") -> 4
A36: Proposed, no statute found | C36: =COUNTIF('Retention Schedule'!$H$5:$H$28,"Proposed") -> 13
A38: How to use
A39: Blue text on yellow cells are inputs. Everything else calculates.
A40: Update Status in the Gap Register and Action Tracker; this page recalculates.
A41: Set a named owner and evidence link on each action. Change a target day on the Action Tracker to re-plan.
A42: Assumptions and sources are on the Lists sheet. Retention law summary is on the Retention Rules sheet.

Sheet Gap Register
A1: Gap Register
A2: One row per finding. Yellow cells are for the team to update. Target date comes from the linked action.
A4: ID | B4: Department | C4: Theme | D4: Finding | E4: Type | F4: Priority | G4: DPDP reference | H4: Source | I4: Action ID | J4: Status | K4: Target date | L4: Named owner | M4: Evidence / remarks
A5: G-001 | B5: VRM & Billing | C5: Messaging channels | D5: DL, Aadhaar, RC, insurance and phone numbers collected on personal WhatsApp after hours; allocation shares bookings there at peak. | E5: Gap | F5: Critical | G5: s.8(5); Rule 6 | H5: VRM & Billing HOD interview, 08 Oct 2026 | I5: A1 | J5: Open | K5: =IFERROR(INDEX('Action Tracker'!$F$5:$F$15,MATCH(I5,'Action Tracker'!$A$5:$A$15,0)),"") -> 46339
A6: G-002 | B6: Fleet | C6: Messaging channels | D6: Vendors send KYC documents over WhatsApp as well as through CabPro. | E6: Gap | F6: High | G6: s.8(5); Rule 6 | H6: Fleet HOD interview, 08 Oct 2026 | I6: A1 | J6: Open | K6: =IFERROR(INDEX('Action Tracker'!$F$5:$F$15,MATCH(I6,'Action Tracker'!$A$5:$A$15,0)),"") -> 46339
A7: G-003 | B7: KAM | C7: Messaging channels | D7: Live driver details, passenger numbers and location pins shared in WhatsApp groups with client travel desks. | E7: Gap | F7: High | G7: s.8(5); Rule 6 | H7: KAM HOD interview, 13 Oct 2026 | I7: A1 | J7: Open | K7: =IFERROR(INDEX('Action Tracker'!$F$5:$F$15,MATCH(I7,'Action Tracker'!$A$5:$A$15,0)),"") -> 46339
A8: G-004 | B8: Sales | C8: Messaging channels | D8: Client contacts, driver requirements and booking requests shared on personal WhatsApp. | E8: Gap | F8: High | G8: s.8(5); Rule 6 | H8: Sales HOD interview, 13 Oct 2026 | I8: A1 | J8: Open | K8: =IFERROR(INDEX('Action Tracker'!$F$5:$F$15,MATCH(I8,'Action Tracker'!$A$5:$A$15,0)),"") -> 46339
A9: G-005 | B9: CAT | C9: Messaging channels | D9: Dispatch details and passenger numbers sent to drivers and fleet vendors in WhatsApp groups and chats. | E9: Gap | F9: High | G9: s.8(5); Rule 6 | H9: CAT HOD interview, 12 Oct 2026 | I9: A1 | J9: Open | K9: =IFERROR(INDEX('Action Tracker'!$F$5:$F$15,MATCH(I9,'Action Tracker'!$A$5:$A$15,0)),"") -> 46339
A10: G-006 | B10: VRM & Billing | C10: ID masking | D10: Full raw scans of Aadhaar, PAN, agreement, cancelled cheque, MSME and GST held on the Insta portal. | E10: Gap | F10: High | G10: s.8(5); minimisation; UIDAI | H10: VRM & Billing HOD interview, 08 Oct 2026 | I10: A2 | J10: Open | K10: =IFERROR(INDEX('Action Tracker'!$F$5:$F$15,MATCH(I10,'Action Tracker'!$A$5:$A$15,0)),"") -> 46429
A11: G-007 | B11: Fleet | C11: ID masking | D11: Unmasked Aadhaar and raw document scans in application databases and backend portals. | E11: Gap | F11: High | G11: s.8(5); minimisation; UIDAI | H11: Fleet HOD interview, 08 Oct 2026 | I11: A2 | J11: Open | K11: =IFERROR(INDEX('Action Tracker'!$F$5:$F$15,MATCH(I11,'Action Tracker'!$A$5:$A$15,0)),"") -> 46429
A12: G-008 | B12: HR | C12: ID masking | D12: Raw Aadhaar, PAN and bank passbook scans in file folders and Keka uploads. | E12: Gap | F12: High | G12: s.8(5); minimisation; UIDAI | H12: HR HOD interview, 14 Oct 2026 | I12: A2 | J12: Open | K12: =IFERROR(INDEX('Action Tracker'!$F$5:$F$15,MATCH(I12,'Action Tracker'!$A$5:$A$15,0)),"") -> 46429
A13: G-009 | B13: Admin | C13: ID masking | D13: Answers conflict on whether guards copy visitor and contractor ID proofs. | E13: Verify | F13: Medium | G13: s.8(5); minimisation; UIDAI | H13: Admin HOD interview, 14 Oct 2026 | I13: A2 | J13: Open | K13: =IFERROR(INDEX('Action Tracker'!$F$5:$F$15,MATCH(I13,'Action Tracker'!$A$5:$A$15,0)),"") -> 46429
A14: G-010 | B14: Accounts & Tax | C14: ID masking | D14: Aadhaar copies may be attached in billing back-up documents held in the ERP. | E14: Verify | F14: Medium | G14: s.8(5); minimisation; UIDAI | H14: Accounts & Tax HOD interview, 14 Oct 2026 | I14: A2 | J14: Open | K14: =IFERROR(INDEX('Action Tracker'!$F$5:$F$15,MATCH(I14,'Action Tracker'!$A$5:$A$15,0)),"") -> 46429
A15: G-011 | B15: VRM & Billing | C15: Local copies | D15: Agents can download full KYC scans to local laptops. | E15: Gap | F15: High | G15: s.8(5); Rule 6 | H15: VRM & Billing HOD interview, 08 Oct 2026 | I15: A3 | J15: Open | K15: =IFERROR(INDEX('Action Tracker'!$F$5:$F$15,MATCH(I15,'Action Tracker'!$A$5:$A$15,0)),"") -> 46429
A16: G-012 | B16: HR | C16: Local copies | D16: Payroll reconciliation, bank files, appraisal logs and employee lists stored on laptops. | E16: Gap | F16: Medium | G16: s.8(5); Rule 6 | H16: HR HOD interview, 14 Oct 2026 | I16: A3 | J16: Open | K16: =IFERROR(INDEX('Action Tracker'!$F$5:$F$15,MATCH(I16,'Action Tracker'!$A$5:$A$15,0)),"") -> 46429
... A62: G-058 | B62: Reservations | C62: Incident response | D62: Incident-response question left unanswered in the interview. | E62: Verify | F62: Medium | G62: s.8(6); Rule 7 | H62: Reservations HOD interview, 12 Oct 2026 | I62: A11 | J62: Open | K62: =IFERROR(INDEX('Action Tracker'!$F$5:$F$15,MATCH(I62,'Action Tracker'!$A$5:$A$15,0)),"") -> 46519

Sheet Action Tracker
A1: Action Tracker
A2: Due date = programme start (Dashboard) + target day. Linked and open findings count from the Gap Register.
A4: ID | B4: Action | C4: Owner (function) | D4: Phase | E4: Target day | F4: Due date | G4: Departments in scope | H4: Linked findings | I4: Open findings | J4: Status | K4: % complete | L4: Named owner | M4: Evidence / link | N4: Remarks
A5: A1 | B5: Ban WhatsApp for personal data; ship CabPro Android upload and driver-app dispatch with masked numbers | C5: IT, Fleet Ops | D5: 1 Contain | E5: 30 | F5: =Dashboard!$C$4+E5 -> 46339 | G5: CAT, Fleet, VRM, KAM, Sales | H5: =COUNTIF('Gap Register'!$I$5:$I$300,A5) -> 6 | I5: =COUNTIFS('Gap Register'!$I$5:$I$300,A5,'Gap Register'!$J$5:$J$300,"<>Closed") -> 6 | J5: Not started | K5: 0
A6: A2 | B6: Mask Aadhaar at ingestion (redact first 8 digits); stop raw image storage; redact existing scans | C6: IT | D6: 2 Build | E6: 120 | F6: =Dashboard!$C$4+E6 -> 46429 | G6: Fleet, VRM, HR (verify Admin, Accounts & Tax) | H6: =COUNTIF('Gap Register'!$I$5:$I$300,A6) -> 5 | I6: =COUNTIFS('Gap Register'!$I$5:$I$300,A6,'Gap Register'!$J$5:$J$300,"<>Closed") -> 5 | J6: Not started | K6: 0
A7: A3 | B7: Deploy endpoint DLP; set systems to view-only; disable bulk export in ERP and CRM | C7: IT Security | D7: 2 Build | E7: 120 | F7: =Dashboard!$C$4+E7 -> 46429 | G7: VRM, HR, KAM, Sales, Admin, Submission, Accounts & Tax, Reservations | H7: =COUNTIF('Gap Register'!$I$5:$I$300,A7) -> 10 | I7: =COUNTIFS('Gap Register'!$I$5:$I$300,A7,'Gap Register'!$J$5:$J$300,"<>Closed") -> 10 | J7: Not started | K7: 0
A8: A4 | B8: Rebuild consent: vendor or driver signs by OTP or eSign, time-stamped; stop agent-signed consent | C8: IT, VRM | D8: 2 Build | E8: 120 | F8: =Dashboard!$C$4+E8 -> 46429 | G8: VRM, Fleet | H8: =COUNTIF('Gap Register'!$I$5:$I$300,A8) -> 1 | I8: =COUNTIFS('Gap Register'!$I$5:$I$300,A8,'Gap Register'!$J$5:$J$300,"<>Closed") -> 1 | J8: Not started | K8: 0
A9: A5 | B9: Publish versioned bilingual privacy notice and a withdrawal path (incl. marketing opt-in and unsubscribe) | C9: DPO, IT | D9: 2 Build | E9: 120 | F9: =Dashboard!$C$4+E9 -> 46429 | G9: VRM, Fleet, Marketing | H9: =COUNTIF('Gap Register'!$I$5:$I$300,A9) -> 4 | I9: =COUNTIFS('Gap Register'!$I$5:$I$300,A9,'Gap Register'!$J$5:$J$300,"<>Closed") -> 4 | J9: Not started | K9: 0
A10: A6 | B10: Approve the retention schedule; automate purge | C10: DPO, IT | D10: 2 Build | E10: 120 | F10: =Dashboard!$C$4+E10 -> 46429 | G10: All 13 | H10: =COUNTIF('Gap Register'!$I$5:$I$300,A10) -> 13 | I10: =COUNTIFS('Gap Register'!$I$5:$I$300,A10,'Gap Register'!$J$5:$J$300,"<>Closed") -> 13 | J10: Not started | K10: 0
A11: A7 | B11: Issue a DPDP-ready DPA; execute with vendors and client MSAs | C11: Legal | D11: 2 Build | E11: 120 | F11: =Dashboard!$C$4+E11 -> 46429 | G11: Fleet, VRM, HR, Sales, Admin, Accounts & Tax, Marketing | H11: =COUNTIF('Gap Register'!$I$5:$I$300,A11) -> 7 | I11: =COUNTIFS('Gap Register'!$I$5:$I$300,A11,'Gap Register'!$J$5:$J$300,"<>Closed") -> 7 | J11: Not started | K11: 0
A12: A8 | B12: Mask names in client MIS; named, expiring links, encrypted ZIPs and a data room for auditors | C12: Billing, KAM leads | D12: 1 Contain | E12: 30 | F12: =Dashboard!$C$4+E12 -> 46339 | G12: Submission, Collection, Accounts & Tax, KAM | H12: =COUNTIF('Gap Register'!$I$5:$I$300,A12) -> 5 | I12: =COUNTIFS('Gap Register'!$I$5:$I$300,A12,'Gap Register'!$J$5:$J$300,"<>Closed") -> 5 | J12: Not started | K12: 0
A13: A9 | B13: Close cross-border checks on Keka/Mynd, ad platforms, Workspace, Drive/OneDrive, CRM | C13: IT, Legal | D13: 3 Sustain | E13: 210 | F13: =Dashboard!$C$4+E13 -> 46519 | G13: HR, Marketing, Reservations, Submission, Sales | H13: =COUNTIF('Gap Register'!$I$5:$I$300,A13) -> 5 | I13: =COUNTIFS('Gap Register'!$I$5:$I$300,A13,'Gap Register'!$J$5:$J$300,"<>Closed") -> 5 | J13: Not started | K13: 0
A14: A10 | B14: Cover the visitor register; set CCTV and access-log retention | C14: Admin | D14: 1 Contain | E14: 30 | F14: =Dashboard!$C$4+E14 -> 46339 | G14: Admin | H14: =COUNTIF('Gap Register'!$I$5:$I$300,A14) -> 1 | I14: =COUNTIFS('Gap Register'!$I$5:$I$300,A14,'Gap Register'!$J$5:$J$300,"<>Closed") -> 1 | J14: Not started | K14: 0
A15: A11 | B15: Update breach SOP for a 72-hour Board report; run a drill; train staff by role | C15: DPO, IT Security | D15: 3 Sustain | E15: 210 | F15: =Dashboard!$C$4+E15 -> 46519 | G15: All 13 | H15: =COUNTIF('Gap Register'!$I$5:$I$300,A15) -> 1 | I15: =COUNTIFS('Gap Register'!$I$5:$I$300,A15,'Gap Register'!$J$5:$J$300,"<>Closed") -> 1 | J15: Not started | K15: 0
A17: Blue text on yellow = input. Target day is an assumption from the roadmap; change it to re-plan. Overdue due dates turn red.

Sheet Retention Schedule
A1: Retention Schedule (proposed)
A2: Basis type: Statutory floor = a law sets a minimum. Stated in interview = the HOD gave the period. Proposed = no statute found; set under DPDP s.8(7) on purpose. Proposed periods are recommendations for Legal and the DPO to approve.
A4: ID | B4: Data category | C4: Departments | D4: Data principals | E4: Clock starts | F4: Statutory minimum | G4: Proposed retention | H4: Basis type | I4: Disposal | J4: Current practice (interviews) | K4: ROPA ID | L4: Owner | M4: Status | N4: Approved by Legal | O4: Notes
A5: T-01 | B5: Books of account, invoices, vouchers, duty slips supporting invoices | C5: Accounts & Tax, Collection, Submission | D5: Clients, drivers, vendors, guests | E5: End of financial year | F5: 8 financial years (Companies Act s.128(5)); GST 72 months; Income-tax 6 years | G5: 8 financial years, then delete or anonymise. Mask guest phone numbers on duty slips after 90 days. | H5: Statutory floor | I5: Secure delete; restricted archive | J5: 8 years stated; deletion manual; guest names in MIS | K5: R-08, R-09, R-10 | L5: Accounts & Tax head | M5: Proposed | N5: No
A6: T-02 | B6: Vendor and driver payout data (bank, PAN, TDS records) | C6: Accounts & Tax | D6: Drivers, vendors | E6: End of FY of last payment | F6: 8 financial years as voucher support | G6: 8 financial years from the FY of last payment, then delete. | H6: Statutory floor | I6: Secure delete | J6: 8 years stated; manual deletion | K6: R-10 | L6: Accounts & Tax head | M6: Proposed | N6: No
A7: T-03 | B7: Driver and vendor KYC scans (Aadhaar, DL, RC, insurance, permits) | C7: Fleet, VRM | D7: Chauffeurs, vehicle owners, vendors | E7: Relationship end | F7: None found for raw copies | G7: Relationship end + 3 years (claims window). Store Aadhaar masked only. Keep only masked copies as payout support. | H7: Proposed | I7: Automated purge job | J7: No purge configured (VRM); Fleet claims automated | K7: R-01 | L7: Fleet / VRM heads | M7: Proposed | N7: No
A8: T-04 | B8: Consent records and privacy notice versions | C8: VRM, Fleet, Marketing | D8: All data principals | E8: Consent withdrawn or relationship end | F8: None | G8: Life of consent + 3 years, as evidence. | H8: Proposed | I8: Secure delete | J8: No notice or version history today | K8: R-01, R-07 | L8: DPO | M8: Proposed | N8: No
A9: T-05 | B9: Booking and dispatch records (name, phone, pickup, drop) | C9: Reservations, CAT, KAM | D9: Passengers, corporate employees | E9: Trip completion | F9: None | G9: 90 days after trip, then remove identifiers. Billing copy is kept under T-01. | H9: Stated in interview | I9: Automated archive then delete | J9: Reservations: 90 days stated; KAM rosters indefinite | K9: R-02, R-03, R-04 | L9: Reservations / CAT heads | M9: Proposed | N9: No
A10: T-06 | B10: Driver app, trip and location logs | C10: CAT, IT | D10: Passengers, chauffeurs | E10: Date of processing | F10: At least 1 year (DPDP Rule 8(3)) | G10: 1 year, then delete unless an incident or claim is open. | H10: Statutory floor | I10: Automated purge | J10: App cache purged post-trip; central retention not seen | K10: R-02 | L10: IT | M10: Proposed | N10: No
A11: T-07 | B11: System, access and security logs | C11: IT Security | D11: All | E11: Date of log | F11: 180 days in India (CERT-In); at least 1 year (DPDP Rule 8(3)) | G11: 1 year (the longer rule), stored in India. | H11: Statutory floor | I11: Automated rotation | J11: Not covered in interviews | L11: IT Security | M11: Proposed | N11: No
A12: T-08 | B12: Corporate client contacts and contract files | C12: CMT, Sales, KAM | D12: Client signatories, travel desks | E12: Contract end | F12: 8 financial years where part of books | G12: Contract end + 8 years for contract and billing file. Deactivate a contact when the client confirms a change. | H12: Stated in interview | I12: Secure delete | J12: CMT states contract + 8 years | K12: R-05, R-06 | L12: CMT head | M12: Proposed | N12: No
A13: T-09 | B13: Client rosters, MIS exports, VIP profiles | C13: KAM, Sales | D13: Client employees, VIPs | E13: Account termination | F13: None | G13: Delete within 90 days of account termination. No local exports. | H13: Proposed | I13: Delete from CRM, email and laptops | J13: Indefinite in email and local drives | K13: R-04, R-05 | L13: KAM / Sales heads | M13: Proposed | N13: No
A14: T-10 | B14: Lost or unconverted B2B leads and RFP contacts | C14: Sales | D14: Prospect contacts | E14: Last contact | F14: None | G14: 12 months from last contact, then delete. | H14: Proposed | I14: Automated CRM purge | J14: Indefinite in CRM | K14: R-05 | L14: Sales head | M14: Proposed | N14: No
A15: T-11 | B15: Marketing leads, app and campaign data | C15: Marketing | D15: Leads, app users | E15: Last engagement | F15: None | G15: 3 months idle (Marketing's figure). Erase on consent withdrawal. | H15: Stated in interview | I15: Automated suppression and delete | J15: 3-month validity claimed; not evidenced | K15: R-07 | L15: Marketing head | M15: Proposed | N15: No
A16: T-12 | B16: Marketing opt-out (suppression) list | C16: Marketing | D16: Leads, customers | E16: Opt-out date | F16: None | G16: Keep the minimum identifier needed to honour the opt-out. | H16: Proposed | I16: Review yearly | J16: Unsubscribe 'not available as of now' | K16: R-07 | L16: Marketing head | M16: Proposed | N16: No
A17: T-13 | B17: Payroll, PF, ESIC and tax records | C17: HR | D17: Employees | E17: End of financial year | F17: 8 FY stated by HR; labour-law periods not verified | G17: 8 financial years. HR and Legal to confirm any longer statutory period. | H17: Stated in interview | I17: Secure delete | J17: 8 years stated | K17: R-11 | L17: HR head | M17: Proposed | N17: No
A18: T-14 | B18: Employee personnel file and appraisals | C18: HR | D18: Employees | E18: Exit date | F18: None found | G18: Exit + 3 years, then delete. | H18: Proposed | I18: Secure delete | J18: Held indefinitely | K18: R-11 | L18: HR head | M18: Proposed | N18: No
A19: T-15 | B19: Rejected applicant resumes | C19: HR | D19: Applicants | E19: Rejection | F19: None | G19: 12 months. Longer only with consent for a talent pool. | H19: Stated in interview | I19: Automated purge in Keka | J19: Indefinite in Keka and local folders | K19: R-11 | L19: HR head | M19: Proposed | N19: No
A20: T-16 | B20: Ex-employee HRMS profile and access | C20: HR, IT | D20: Ex-employees | E20: Exit date | F20: Statutory payroll records only | G20: Revoke access on exit day. Keep only the records under T-13 and T-14. | H20: Proposed | I20: Access revocation checklist | J20: Profiles remain in Keka indefinitely | K20: R-11 | L20: HR / IT | M20: Proposed | N20: No
A21: T-17 | B21: Visitor registers and gate records | C21: Admin | D21: Visitors, contractors | E21: Visit date | F21: None | G21: 12 months. Paper register must not be left open. | H21: Proposed | I21: Shred or delete | J21: Indefinite; register open to later visitors | K21: R-12 | L21: Admin head | M21: Proposed | N21: No
A22: T-18 | B22: CCTV footage | C22: Admin | D22: Staff, visitors | E22: Recording date | F22: None | G22: 90 days. Hold longer only for a flagged incident. | H22: Proposed | I22: Automatic overwrite | J22: Kept until storage fills | K22: R-12 | L22: Admin head | M22: Proposed | N22: No
A23: T-19 | B23: Biometric and access-card logs | C23: Admin, HR | D23: Employees, visitors | E23: Date of log | F23: Possibly Rule 8(3), 1 year; confirm with Legal | G23: 1 year. Attendance summaries are kept under T-13. | H23: Proposed | I23: Automated purge | J23: No documented purge | K23: R-11, R-12 | L23: Admin / HR | M23: Proposed | N23: No
... A25: T-21 | B25: Shared cloud links for invoices and duty slips | C25: Submission | D25: Billing contacts, passengers on slips | E25: Link creation | F25: None | G25: 30 days maximum, named recipients, password. | H25: Stated in interview | I25: Link expiry | J25: 30 days approved by HOD; links not always restricted | K25: R-08 | L25: Submission head | M25: Proposed | N25: No
A26: T-22 | B26: Breach register and incident records | C26: DPO, IT Security | D26: Affected principals | E26: Incident closure | F26: None | G26: 3 years after closure. Keep the Board report copy as long. | H26: Proposed | I26: Secure delete | J26: Register exists per HODs; not seen | L26: DPO | M26: Proposed | N26: No
A27: T-23 | B27: Data principal requests (access, correction, erasure, withdrawal) | C27: DPO | D27: Requesters | E27: Request closure | F27: None | G27: 3 years after closure. | H27: Proposed | I27: Secure delete | J27: No workflow today | L27: DPO | M27: Proposed | N27: No
A28: T-24 | B28: Contracts, NDAs and DPAs | C28: Legal, CMT, Fleet | D28: Signatories | E28: Termination | F28: None | G28: Termination + 8 years (CMT's contractual liability figure). | H28: Stated in interview | I28: Secure delete | J28: Not defined outside CMT | K28: R-06 | L28: Legal | M28: Proposed | N28: No

Sheet Retention Rules
A1: Retention Rules: what applies to Carzonrent
A2: Bottom line: the DPDP Act sets no fixed retention period for a company like Carzonrent. Section 8(7) requires erasure once the purpose is served or consent is withdrawn, unless another law requires retention. So Carzonrent must set its own purpose-based periods, and keep tax, company-law and log records for the periods those laws require.
A4: Rule | B4: What it says | C4: Applies to Carzonrent? | D4: What to do | E4: Source | F4: Verified?
A5: DPDP Act s.8(7) | B5: Erase personal data when consent is withdrawn or it is reasonable to assume the purpose is no longer served, unless retention is necessary to comply with a law. No fixed period. | C5: Yes, from about May 2027 | D5: Set a purpose-based period for every data category (Retention Schedule). Document the reason. Automate deletion. | E5: DPDP Act 2023; summary at sansalegal.com (DPDP Rules 2025 retention schedule guide) | F5: Checked against a secondary source
A6: DPDP Rules 2025, Rule 8(1) and Third Schedule | B6: Fixed 3-year period (from the user's last interaction) for e-commerce entities with 2 crore or more users, online gaming intermediaries with 50 lakh or more, and social media intermediaries with 2 crore or more. | C6: Very unlikely. Confirm registered-user count and that Carzonrent is not an e-commerce entity at that scale. | D6: No fixed 3-year period applies. Use the company schedule. | E6: DPDP Rules 2025 via sansalegal.com | F6: Checked against a secondary source; Legal to confirm
A7: DPDP Rules 2025, Rule 8(2) | B7: 48 hours' notice to the user before erasure, for the Third Schedule classes. | C7: Not required for Carzonrent on the above | D7: Optional good practice for customer-facing erasure. | E7: sansalegal.com | F7: Checked against a secondary source
A8: DPDP Rules 2025, Rule 8(3) | B8: Retain personal data, associated traffic data and processing logs for at least one year, for the purposes the Rules specify. | C8: Yes, for logs | D8: Keep processing, access and trip logs at least 1 year, then delete unless another law needs longer. | E8: sansalegal.com | F8: Checked against a secondary source; Legal to confirm scope
A9: DPDP Act s.6(6) and s.12(3) | B9: On withdrawal of consent, stop processing (and make processors stop). On a user's erasure request, erase unless needed for the purpose or to comply with law. | C9: Yes | D9: Build a withdrawal and erasure workflow, including fleet vendors and other processors. | E9: sansalegal.com | F9: Checked against a secondary source
A10: Companies Act 2013 s.128(5) | B10: Books of account and vouchers: at least the 8 financial years immediately preceding the current one. | C10: Yes | D10: Keep books, invoices, vouchers and supporting duty slips for 8 financial years. | E10: metalegal.in (maintenance of records) | F10: Checked against a secondary source
A11: Income-tax Rules 1962, Rule 6F(5) | B11: Books and documents: at least 6 years from the end of the relevant assessment year. | C11: Yes, but the Income-tax Act 2025 replaces the 1961 Act from 1 April 2026; confirm the equivalent rule | D11: The 8-year Companies Act period is longer, so 8 financial years covers it. | E11: metalegal.in | F11: Checked for the 1961 Act only; Legal to confirm under the 2025 Act
A12: CGST Act s.36 and Rule 56 | B12: Accounts and records: 72 months from the due date of the annual return for the year; longer if proceedings are pending. | C12: Yes | D12: Covered by the 8-year books period; extend for pending proceedings. | E12: taxguru.in / metalegal.in | F12: Checked against a secondary source
A13: CERT-In Directions 2022 | B13: Keep ICT system logs for a rolling 180 days within India; report cyber incidents within 6 hours. | C13: Yes | D13: Keep logs 1 year (the longer DPDP floor), stored in India. | E13: mondaq.com (overview of CERT-In directions) | F13: Checked against a secondary source
A14: Labour laws (PF, ESIC, Gratuity, Payment of Wages, Contract Labour) | B14: Record-keeping periods differ by statute. | C14: Yes for employees | D14: HR and Legal to list the exact period per statute. Until then HR's stated 8 financial years applies. | E14: Not verified in this review | F14: NOT verified
A15: Limitation Act 1963 | B15: General limitation of 3 years for most civil claims. | C15: Used as the basis for dispute windows (proposal, not a retention rule) | D15: Used to justify relationship end + 3 years for KYC, consent and personnel records. Legal to confirm. | E15: General legal principle | F15: Not verified here; Legal to confirm

Sheet ROPA
A1: ROPA: Record of Processing Activities
A2: Lawful basis is proposed for Legal to confirm. Retention is as stated by the HOD. Yellow cells are for owners to complete.
A4: ROPA ID | B4: Department | C4: Processing activity | D4: Data principals | E4: Data categories | F4: Purpose | G4: Proposed lawful basis | H4: Systems | I4: Recipients | J4: Cross-border | K4: Retention (as stated) | L4: Retention gap? | M4: Owner (HOD) | N4: Last reviewed | O4: Status
A5: R-01 | B5: Fleet, VRM | C5: Driver and vendor onboarding | D5: Chauffeurs, vehicle owners, fleet vendors | E5: Aadhaar, PAN, DL, bank details, RC, insurance, fitness/permits, cancelled cheque, consent letter, contact details | F5: Verify eligibility, TDS and payouts, vendor contracts | G5: Consent (s.6) plus legal obligation (tax) | H5: CabPro, Insta portal | I5: Accounts, Allocation | J5: No | K5: 8 years for tax; automated purge not built | L5: Yes | O5: Draft
A6: R-02 | B6: CAT | C6: Trip allocation and dispatch | D6: Passengers, chauffeurs | E6: Passenger name and phone, pickup and drop, chauffeur name, phone and DL number, vehicle | F6: Allocate cars, dispatch drivers, passenger safety | G6: Voluntary provision for the requested service (s.7) | H6: Dispatch system, driver app, WhatsApp (to retire) | I6: Fleet vendors, chauffeurs | J6: Not asked | K6: Central retention schedule; app cache purged post-trip | L6: To verify | O6: Draft
A7: R-03 | B7: Reservations | C7: Corporate booking intake | D7: Corporate employees | E7: Name, phone, pickup and drop, flight or train details, travel time, special instructions, billing identifiers | F7: Arrange transport, calculate ETAs, billing | G7: Voluntary provision for the requested service (s.7) | H7: Google Workspace mail, booking software | I7: KAM, Ops, client travel desk | J7: To verify | K7: 90 days after trip (stated) | L7: To verify | O7: Draft
A8: R-04 | B8: KAM | C8: Key account servicing | D8: Client travel desks, employees, VIPs | E8: Contacts, employee ID, cost centre, itineraries, flight numbers, VIP preferences, driver assignment | F8: Bookings, escalations, MIS, account reviews | G8: Voluntary provision for the requested service (s.7) | H8: Insta ERP, email, WhatsApp groups (to retire) | I8: Dispatch, client travel desks | J8: No | K8: Billing 8 years; rosters and logs indefinite | L8: Yes | O8: Draft
A9: R-05 | B9: Sales | C9: B2B sales and RFPs | D9: Travel managers, procurement officers | E9: Name, designation, email, phone, address, GSTIN, corporate bank details | F9: Evaluate bids, negotiate rate contracts, set up billing | G9: Contract; voluntary provision (s.7) | H9: CRM, Insta ERP, email, WhatsApp (to retire) | I9: CMT, Ops, Billing | J9: To verify | K9: Contract plus 8 years; lost leads indefinite | L9: Yes | O9: Draft
A10: R-06 | B10: CMT | C10: Corporate contract management | D10: Authorised signatories | E10: Name, email, phone, designation, contract and billing terms, GST copy | F10: Execute B2B agreements, create client in Insta ERP, collections | G10: Contract | H10: Insta ERP, CMT file server, SRM archive | I10: Accounts, KAM, Legal, Sales | J10: No | K10: Contract plus 8 years | L10: To verify | O10: Draft
A11: R-07 | B11: Marketing | C11: Campaigns and lead generation | D11: Leads, app users, event registrants | E11: Name, phone, email, location, vehicle preference, booking history, app behaviour, response logs | F11: Targeted offers, loyalty programmes, ROI analysis | G11: Consent (s.6) | H11: Insta CRM, app.chati.ai, Google Ads, Meta Ads, email providers | I11: Ad networks, email gateways, Sales | J11: Yes | K11: 3 months for idle leads (stated) | L11: To verify | O11: Draft
A12: R-08 | B12: Submission | C12: Invoice submission | D12: Corporate billing contacts, passengers, chauffeurs | E12: Billing contacts, passenger and chauffeur details on duty slips, vehicle numbers, payment schedules | F12: Corporate billing, trip validation, client audit | G12: Contract | H12: Insta ERP, email, courier, Drive/OneDrive links | I12: Corporate client billing teams | J12: To verify | K12: Shared links expire in 30 days | L12: To verify | O12: Draft
A13: R-09 | B13: Collection | C13: Collections and reconciliation | D13: Client contacts, guests | E13: Contact details, guest names in MIS, bank details, transaction IDs, remittance advice | F13: Payment follow-up, reconciliation, tax invoices | G13: Contract; legal obligation | H13: Oracle ERP, Insta ERP, email | I13: Finance, financial auditors | J13: No | K13: 8 financial years | L13: To verify | O13: Draft
A14: R-10 | B14: Accounts & Tax | C14: Payouts, TDS and GST | D14: Drivers, vendors, employees | E14: Bank account, IFSC, PAN, GSTIN, trip earnings, TDS records, reimbursement claims | F14: Vendor payouts, TDS and GST returns, audits | G14: Legal obligation (s.7) | H14: Oracle ERP, Insta ERP | I14: Banks, GSTN, TRACES, financial auditors | J14: No | K14: 8 financial years; deletion manual | L14: Yes | O14: Draft
A15: R-11 | B15: HR | C15: Recruitment, payroll and attendance | D15: Employees, applicants | E15: Name, DOB, address, Aadhaar, PAN, bank, PF and ESIC numbers, health insurance, attendance, appraisals | F15: Payroll, statutory dues, insurance, performance | G15: Employment and legal obligation (s.7) | H15: Keka HRMS, Mynd Solutions, biometric | I15: PF, ESIC, tax authorities, banks | J15: To verify | K15: Payroll 8 years; resumes and ex-employee files indefinite | L15: Yes | O15: Draft
A16: R-12 | B16: Admin | C16: Visitor, facility and asset records | D16: Visitors, contractors, facility vendors | E16: Name, phone, email, company, ID details, vehicle number, photo, vendor bank details, asset allocation | F16: Site security, access control, vendor payments | G16: Voluntary provision; contract (s.7) | H16: Paper register, biometric, CCTV, Excel | I16: Facility and security vendors | J16: No | K16: CCTV and logs kept indefinitely | L16: Yes | O16: Draft
A18: Still to capture: retail bookings (CRM mailbox), app and web bookings, Finance payouts team, IT, Legal. Add rows below as they are interviewed.

Sheet Departments
A1: Department status
A2: Rating is preliminary (reviewer's synthesis). Counts are live from the Gap Register.
A4: Department | B4: Interview date | C4: Preliminary rating | D4: Gaps | E4: Verify items | F4: Open findings | G4: Action tracker in form | H4: HOD declaration signed | I4: Evidence pack received | J4: Key issue
A5: VRM & Billing | B5: 46303 | C5: Critical | D5: =COUNTIFS('Gap Register'!$B$5:$B$300,A5,'Gap Register'!$E$5:$E$300,"Gap") -> 8 | E5: =COUNTIFS('Gap Register'!$B$5:$B$300,A5,'Gap Register'!$E$5:$E$300,"Verify") -> 0 | F5: =COUNTIFS('Gap Register'!$B$5:$B$300,A5,'Gap Register'!$J$5:$J$300,"<>Closed") -> 8 | G5: Completed | H5: No | I5: No | J5: Agents sign consent for vendors; no notice; raw Aadhaar; WhatsApp intake; no valid DPA.
A6: Fleet | B6: 46303 | C6: Critical | D6: =COUNTIFS('Gap Register'!$B$5:$B$300,A6,'Gap Register'!$E$5:$E$300,"Gap") -> 3 | E6: =COUNTIFS('Gap Register'!$B$5:$B$300,A6,'Gap Register'!$E$5:$E$300,"Verify") -> 3 | F6: =COUNTIFS('Gap Register'!$B$5:$B$300,A6,'Gap Register'!$J$5:$J$300,"<>Closed") -> 6 | G6: Blank | H6: No | I6: No | J6: Unmasked Aadhaar in databases; KYC over WhatsApp; no NDA or DPA with vendors.
A7: HR | B7: 46309 | C7: High | D7: =COUNTIFS('Gap Register'!$B$5:$B$300,A7,'Gap Register'!$E$5:$E$300,"Gap") -> 4 | E7: =COUNTIFS('Gap Register'!$B$5:$B$300,A7,'Gap Register'!$E$5:$E$300,"Verify") -> 1 | F7: =COUNTIFS('Gap Register'!$B$5:$B$300,A7,'Gap Register'!$J$5:$J$300,"<>Closed") -> 5 | G7: Blank | H7: No | I7: No | J7: Raw ID scans; payroll files on laptops; resumes kept indefinitely; vendor terms and hosting.
A8: KAM | B8: 46308 | C8: High | D8: =COUNTIFS('Gap Register'!$B$5:$B$300,A8,'Gap Register'!$E$5:$E$300,"Gap") -> 4 | E8: =COUNTIFS('Gap Register'!$B$5:$B$300,A8,'Gap Register'!$E$5:$E$300,"Verify") -> 0 | F8: =COUNTIFS('Gap Register'!$B$5:$B$300,A8,'Gap Register'!$J$5:$J$300,"<>Closed") -> 4 | G8: Blank | H8: No | I8: No | J8: WhatsApp groups with clients; VIP files unencrypted; rosters kept indefinitely; bulk export.
A9: Sales | B9: 46308 | C9: High | D9: =COUNTIFS('Gap Register'!$B$5:$B$300,A9,'Gap Register'!$E$5:$E$300,"Gap") -> 5 | E9: =COUNTIFS('Gap Register'!$B$5:$B$300,A9,'Gap Register'!$E$5:$E$300,"Verify") -> 1 | F9: =COUNTIFS('Gap Register'!$B$5:$B$300,A9,'Gap Register'!$J$5:$J$300,"<>Closed") -> 6 | G9: Blank | H9: No | I9: No | J9: WhatsApp with clients; NDA-only MSAs; CRM export open; lost leads never purged.
A10: CAT | B10: 46307 | C10: High | D10: =COUNTIFS('Gap Register'!$B$5:$B$300,A10,'Gap Register'!$E$5:$E$300,"Gap") -> 1 | E10: =COUNTIFS('Gap Register'!$B$5:$B$300,A10,'Gap Register'!$E$5:$E$300,"Verify") -> 1 | F10: =COUNTIFS('Gap Register'!$B$5:$B$300,A10,'Gap Register'!$J$5:$J$300,"<>Closed") -> 2 | G10: Blank | H10: No | I10: No | J10: Dispatch with passenger numbers goes out over WhatsApp groups and chats.
A11: Marketing | B11: 46307 | C11: High | D11: =COUNTIFS('Gap Register'!$B$5:$B$300,A11,'Gap Register'!$E$5:$E$300,"Gap") -> 1 | E11: =COUNTIFS('Gap Register'!$B$5:$B$300,A11,'Gap Register'!$E$5:$E$300,"Verify") -> 3 | F11: =COUNTIFS('Gap Register'!$B$5:$B$300,A11,'Gap Register'!$J$5:$J$300,"<>Closed") -> 4 | G11: Not in form | H11: No | I11: No | J11: Consent and unsubscribe not in place; cross-border platforms; agency DPAs unseen.
A12: Admin | B12: 46309 | C12: High | D12: =COUNTIFS('Gap Register'!$B$5:$B$300,A12,'Gap Register'!$E$5:$E$300,"Gap") -> 4 | E12: =COUNTIFS('Gap Register'!$B$5:$B$300,A12,'Gap Register'!$E$5:$E$300,"Verify") -> 1 | F12: =COUNTIFS('Gap Register'!$B$5:$B$300,A12,'Gap Register'!$J$5:$J$300,"<>Closed") -> 5 | G12: Blank | H12: No | I12: No | J12: Open visitor register; CCTV kept until full; vendor lists on desktops; ID answers conflict.
A13: Submission | B13: 46303 | C13: Medium | D13: =COUNTIFS('Gap Register'!$B$5:$B$300,A13,'Gap Register'!$E$5:$E$300,"Gap") -> 2 | E13: =COUNTIFS('Gap Register'!$B$5:$B$300,A13,'Gap Register'!$E$5:$E$300,"Verify") -> 2 | F13: =COUNTIFS('Gap Register'!$B$5:$B$300,A13,'Gap Register'!$J$5:$J$300,"<>Closed") -> 4 | G13: Completed | H13: No | I13: No | J13: Drive links and unencrypted ZIPs; duty slip copies on desktops.
A14: Accounts & Tax | B14: 46309 | C14: Medium | D14: =COUNTIFS('Gap Register'!$B$5:$B$300,A14,'Gap Register'!$E$5:$E$300,"Gap") -> 2 | E14: =COUNTIFS('Gap Register'!$B$5:$B$300,A14,'Gap Register'!$E$5:$E$300,"Verify") -> 4 | F14: =COUNTIFS('Gap Register'!$B$5:$B$300,A14,'Gap Register'!$J$5:$J$300,"<>Closed") -> 6 | G14: Completed | H14: No | I14: No | J14: Auditor files by loose email (High item); exports on laptops; manual deletion.
A15: Collection | B15: 46304 | C15: Medium | D15: =COUNTIFS('Gap Register'!$B$5:$B$300,A15,'Gap Register'!$E$5:$E$300,"Gap") -> 1 | E15: =COUNTIFS('Gap Register'!$B$5:$B$300,A15,'Gap Register'!$E$5:$E$300,"Verify") -> 2 | F15: =COUNTIFS('Gap Register'!$B$5:$B$300,A15,'Gap Register'!$J$5:$J$300,"<>Closed") -> 3 | G15: Not in form | H15: No | I15: No | J15: Guest names in MIS on request; DLP claimed but not evidenced.
A16: Reservations | B16: 46307 | C16: Medium | D16: =COUNTIFS('Gap Register'!$B$5:$B$300,A16,'Gap Register'!$E$5:$E$300,"Gap") -> 1 | E16: =COUNTIFS('Gap Register'!$B$5:$B$300,A16,'Gap Register'!$E$5:$E$300,"Verify") -> 3 | F16: =COUNTIFS('Gap Register'!$B$5:$B$300,A16,'Gap Register'!$J$5:$J$300,"<>Closed") -> 4 | G16: Not in form | H16: No | I16: No | J16: Manifests exported to laptops; mail region unconfirmed; incident answer blank.
A17: CMT | B17: 46307 | C17: Low | D17: =COUNTIFS('Gap Register'!$B$5:$B$300,A17,'Gap Register'!$E$5:$E$300,"Gap") -> 0 | E17: =COUNTIFS('Gap Register'!$B$5:$B$300,A17,'Gap Register'!$E$5:$E$300,"Verify") -> 1 | F17: =COUNTIFS('Gap Register'!$B$5:$B$300,A17,'Gap Register'!$J$5:$J$300,"<>Closed") -> 1 | G17: Blank | H17: No | I17: No | J17: Restricted server and locked archives; hand-offs by email only.
A19: Total | D19: =SUM(D5:D17) -> 36 | E19: =SUM(E5:E17) -> 22 | F19: =SUM(F5:F17) -> 58

Sheet Lists
A1: Lists and assumptions
A3: Finding status | B3: Action status | C3: Rating / priority | D3: Yes / No / Partial | E3: Type | F3: ROPA status | G3: Departments | H3: Retention status
A4: Open | B4: Not started | C4: Critical | D4: Yes | E4: Gap | F4: Draft | G4: VRM & Billing | H4: Draft
A5: In progress | B5: In progress | C5: High | D5: No | E5: Verify | F5: Reviewed by owner | G5: Fleet | H5: Proposed
A6: Evidence received | B6: Blocked | C6: Medium | D6: Partial | F6: Approved by Legal | G6: Submission | H6: Approved by Legal
A7: Closed | B7: Complete | C7: Low | G7: Collection | H7: Implemented
G8: CAT
G9: CMT
G10: Marketing
G11: Reservations
G12: Sales
G13: KAM
A14: Assumptions and sources | G14: Accounts & Tax
A15: 1. Findings, ratings and ROPA content come from 13 HOD interviews held 8 to 14 October 2026. | G15: Admin
A16: 2. Priority and preliminary department ratings are the reviewer's synthesis, not auditor scores. Only VRM, Submission and Accounts & Tax trackers carried auditor scores. | G16: HR
A17: 3. Gap = confirmed in the interview. Verify = control claimed or risk conditional; evidence needed.
A18: 4. Target days follow the roadmap: Day 30 Contain, Day 120 Build, Day 210 Sustain. Day 210 from 14 Oct 2026 is 12 May 2027.
A19: 5. Main DPDP Rules duties start about 13 May 2027 (18 months from notification on 13 Nov 2025). Source: DPDP Rules 2025 via Mondaq. Legal to confirm.
A20: 6. DPDP section and rule references are indicative. Legal to confirm.
A21: 7. Proposed lawful bases in the ROPA are for Legal to confirm.
